{
  "source": "app_store",
  "competitor": "natwest",
  "enriched_count": 10,
  "model": "sample-corpus-v1",
  "schema_version": "v3",
  "records": [
    {
      "rating": 5,
      "title": "Review 001",
      "review": "Best banking app I have used.",
      "version": "8.20.1",
      "date": "2026-04-30T00:00:00+00:00",
      "author": "Anon Reviewer 000",
      "issue_type": "Positive Feedback",
      "customer_journey": "General App Use",
      "sentiment_score": 0.8,
      "severity_class": "P2",
      "reasoning": "Generally pleased with the app \u2014 works well."
    },
    {
      "rating": 2,
      "title": "Review 002",
      "review": "Transactions feed is incomplete.",
      "version": "8.20.1",
      "date": "2026-04-28T16:47:00+00:00",
      "author": "Daily Banker 001",
      "issue_type": "Missing Transaction",
      "customer_journey": "Payments",
      "sentiment_score": -0.7,
      "severity_class": "P0",
      "reasoning": "A recent transaction is missing from the feed."
    },
    {
      "rating": 1,
      "title": "Review 003",
      "review": "Transactions feed is incomplete.",
      "version": "8.20.1",
      "date": "2026-04-27T09:34:00+00:00",
      "author": "Sample Customer 002",
      "issue_type": "Missing Transaction",
      "customer_journey": "Payments",
      "sentiment_score": -0.7,
      "severity_class": "P0",
      "reasoning": "A recent transaction is missing from the feed."
    },
    {
      "rating": 2,
      "title": "Review 004",
      "review": "Tried three times to pay a bill \u2014 all failed.",
      "version": "8.20.1",
      "date": "2026-04-26T02:21:00+00:00",
      "author": "App Reviewer 003",
      "issue_type": "Payment Failed",
      "customer_journey": "Payments",
      "sentiment_score": -0.8,
      "severity_class": "P0",
      "reasoning": "Payment did not go through and money was held."
    },
    {
      "rating": 2,
      "title": "Review 005",
      "review": "Account suspended without warning.",
      "version": "8.20.1",
      "date": "2026-04-25T19:08:00+00:00",
      "author": "Frequent User 004",
      "issue_type": "Account Locked",
      "customer_journey": "Account Service",
      "sentiment_score": -0.8,
      "severity_class": "P0",
      "reasoning": "Account locked with no clear reason or recovery path."
    },
    {
      "rating": 1,
      "title": "Review 006",
      "review": "Three days waiting for a callback.",
      "version": "8.20.1",
      "date": "2026-04-24T12:55:00+00:00",
      "author": "Frequent User 005",
      "issue_type": "Customer Service",
      "customer_journey": "Account Service",
      "sentiment_score": -0.6,
      "severity_class": "P1",
      "reasoning": "Could not reach a human agent for a real problem."
    },
    {
      "rating": 2,
      "title": "Review 007",
      "review": "Available balance does not match my actual money.",
      "version": "8.20.1",
      "date": "2026-04-23T05:42:00+00:00",
      "author": "Banking Test 006",
      "issue_type": "Incorrect Balance",
      "customer_journey": "Payments",
      "sentiment_score": -0.7,
      "severity_class": "P0",
      "reasoning": "Displayed balance does not match actual balance."
    },
    {
      "rating": 3,
      "title": "Review 008",
      "review": "Cannot make any payments since the update.",
      "version": "8.20.1",
      "date": "2026-04-22T22:29:00+00:00",
      "author": "Frequent User 007",
      "issue_type": "Payment Failed",
      "customer_journey": "Payments",
      "sentiment_score": -0.8,
      "severity_class": "P0",
      "reasoning": "Payment did not go through and money was held."
    },
    {
      "rating": 1,
      "title": "Review 009",
      "review": "The savings feature stopped working.",
      "version": "8.20.1",
      "date": "2026-04-21T15:16:00+00:00",
      "author": "App Reviewer 008",
      "issue_type": "Feature Broken",
      "customer_journey": "General App Use",
      "sentiment_score": -0.5,
      "severity_class": "P1",
      "reasoning": "A specific feature stopped working after the update."
    },
    {
      "rating": 1,
      "title": "Review 010",
      "review": "App will not open at all after the update.",
      "version": "8.20.1",
      "date": "2026-04-20T08:03:00+00:00",
      "author": "Anon Reviewer 009",
      "issue_type": "App Not Opening",
      "customer_journey": "General App Use",
      "sentiment_score": -0.9,
      "severity_class": "P0",
      "reasoning": "App refuses to open after the latest update."
    }
  ]
}